reverievis/__init__.py
reverievis/charts/__init__.py
reverievis/charts/radar.py
reverievis/core/__init__.py
reverievis/core/base.py
reverievis/core/config.py
reverievis/core/constants.py
reverievis/core/exceptions.py
reverievis/core/factory.py
reverievis/core/themes.py
reverievis/utils/__init__.py
reverievis/utils/chart_utils.py
reverievis/utils/data_utils.py
reverievis-1.0.0.dist-info/licenses/LICENSE
reverievis-1.0.0.dist-info/METADATA
reverievis-1.0.0.dist-info/WHEEL
reverievis-1.0.0.dist-info/top_level.txt
reverievis-1.0.0.dist-info/RECORD
